gempaterkini/__init__.py
realtime_earthquake_indonesia-0.0.4.dist-info/LICENSE
realtime_earthquake_indonesia-0.0.4.dist-info/METADATA
realtime_earthquake_indonesia-0.0.4.dist-info/WHEEL
realtime_earthquake_indonesia-0.0.4.dist-info/top_level.txt
realtime_earthquake_indonesia-0.0.4.dist-info/RECORD
